{
  "byClass": {
    "Aquaculture": {
      "name": "Aquaculture",
      "value": 0,
      "percValue": 0,
      "sketchMetrics": [
        {
          "id": "615c6af3aac8c8285d50dc42",
          "name": "mpa-no-desig",
          "value": 0,
          "percValue": 0
        }
      ]
    },
    "Boating": {
      "name": "Boating",
      "value": 1402.5762112140656,
      "percValue": 0.003259182534592635,
      "sketchMetrics": [
        {
          "id": "615c6af3aac8c8285d50dc42",
          "name": "mpa-no-desig",
          "value": 1402.5762112140656,
          "percValue": 0.003259182534592635
        }
      ]
    },
    "CommercialFishing": {
      "name": "CommercialFishing",
      "value": 1279.6457659006119,
      "percValue": 0.0043189286912403545,
      "sketchMetrics": [
        {
          "id": "615c6af3aac8c8285d50dc42",
          "name": "mpa-no-desig",
          "value": 1279.6457659006119,
          "percValue": 0.0043189286912403545
        }
      ]
    },
    "PassiveRecreation_Conservation": {
      "name": "PassiveRecreation_Conservation",
      "value": 3005.5058405399323,
      "percValue": 0.013019254451483851,
      "sketchMetrics": [
        {
          "id": "615c6af3aac8c8285d50dc42",
          "name": "mpa-no-desig",
          "value": 3005.5058405399323,
          "percValue": 0.013019254451483851
        }
      ]
    },
    "Recreational Fishing": {
      "name": "Recreational Fishing",
      "value": 1693.5159249305725,
      "percValue": 0.007329627199075819,
      "sketchMetrics": [
        {
          "id": "615c6af3aac8c8285d50dc42",
          "name": "mpa-no-desig",
          "value": 1693.5159249305725,
          "percValue": 0.007329627199075819
        }
      ]
    },
    "Shipping": {
      "name": "Shipping",
      "value": 22.123689651489258,
      "percValue": 0.0014980600672898083,
      "sketchMetrics": [
        {
          "id": "615c6af3aac8c8285d50dc42",
          "name": "mpa-no-desig",
          "value": 22.123689651489258,
          "percValue": 0.0014980600672898083
        }
      ]
    },
    "Swimming_Snorkeling_Diving": {
      "name": "Swimming_Snorkeling_Diving",
      "value": 14437.039018332958,
      "percValue": 0.02352230111268414,
      "sketchMetrics": [
        {
          "id": "615c6af3aac8c8285d50dc42",
          "name": "mpa-no-desig",
          "value": 14437.039018332958,
          "percValue": 0.02352230111268414
        }
      ]
    },
    "Tourism": {
      "name": "Tourism",
      "value": 0,
      "percValue": 0,
      "sketchMetrics": [
        {
          "id": "615c6af3aac8c8285d50dc42",
          "name": "mpa-no-desig",
          "value": 0,
          "percValue": 0
        }
      ]
    },
    "Utilities": {
      "name": "Utilities",
      "value": 0,
      "percValue": 0,
      "sketchMetrics": [
        {
          "id": "615c6af3aac8c8285d50dc42",
          "name": "mpa-no-desig",
          "value": 0,
          "percValue": 0
        }
      ]
    }
  }
}