{
  "metrics": [
    {
      "reportId": "habitatProtection",
      "metricId": "nearshore",
      "classId": "Algal Vermetid Reef",
      "sketchId": "61649a3c1e0a596510ad8329",
      "value": 8,
      "extra": {
        "sketchName": "nearshore-span"
      }
    },
    {
      "reportId": "habitatProtection",
      "metricId": "nearshore",
      "classId": "Bathypelagic",
      "sketchId": "61649a3c1e0a596510ad8329",
      "value": 16023,
      "extra": {
        "sketchName": "nearshore-span"
      }
    },
    {
      "reportId": "habitatProtection",
      "metricId": "nearshore",
      "classId": "Bays and Coast",
      "sketchId": "61649a3c1e0a596510ad8329",
      "value": 94,
      "extra": {
        "sketchName": "nearshore-span"
      }
    },
    {
      "reportId": "habitatProtection",
      "metricId": "nearshore",
      "classId": "Castle Harbour Madracis",
      "sketchId": "61649a3c1e0a596510ad8329",
      "value": 0,
      "extra": {
        "sketchName": "nearshore-span"
      }
    },
    {
      "reportId": "habitatProtection",
      "metricId": "nearshore",
      "classId": "Diploria Porites Reef",
      "sketchId": "61649a3c1e0a596510ad8329",
      "value": 4823,
      "extra": {
        "sketchName": "nearshore-span"
      }
    },
    {
      "reportId": "habitatProtection",
      "metricId": "nearshore",
      "classId": "Fore Reef",
      "sketchId": "61649a3c1e0a596510ad8329",
      "value": 510,
      "extra": {
        "sketchName": "nearshore-span"
      }
    },
    {
      "reportId": "habitatProtection",
      "metricId": "nearshore",
      "classId": "Madracis Reef",
      "sketchId": "61649a3c1e0a596510ad8329",
      "value": 0,
      "extra": {
        "sketchName": "nearshore-span"
      }
    },
    {
      "reportId": "habitatProtection",
      "metricId": "nearshore",
      "classId": "Main Terrace Reef",
      "sketchId": "61649a3c1e0a596510ad8329",
      "value": 7934,
      "extra": {
        "sketchName": "nearshore-span"
      }
    },
    {
      "reportId": "habitatProtection",
      "metricId": "nearshore",
      "classId": "Mesopelagic",
      "sketchId": "61649a3c1e0a596510ad8329",
      "value": 5608,
      "extra": {
        "sketchName": "nearshore-span"
      }
    },
    {
      "reportId": "habitatProtection",
      "metricId": "nearshore",
      "classId": "Mesophotic",
      "sketchId": "61649a3c1e0a596510ad8329",
      "value": 2021,
      "extra": {
        "sketchName": "nearshore-span"
      }
    },
    {
      "reportId": "habitatProtection",
      "metricId": "nearshore",
      "classId": "Montastraea Reef",
      "sketchId": "61649a3c1e0a596510ad8329",
      "value": 0,
      "extra": {
        "sketchName": "nearshore-span"
      }
    },
    {
      "reportId": "habitatProtection",
      "metricId": "nearshore",
      "classId": "Rariphotic",
      "sketchId": "61649a3c1e0a596510ad8329",
      "value": 2134,
      "extra": {
        "sketchName": "nearshore-span"
      }
    },
    {
      "reportId": "habitatProtection",
      "metricId": "nearshore",
      "classId": "Rim Reef",
      "sketchId": "61649a3c1e0a596510ad8329",
      "value": 1750,
      "extra": {
        "sketchName": "nearshore-span"
      }
    },
    {
      "reportId": "habitatProtection",
      "classId": "Abyssopelagic",
      "metricId": "offshore",
      "sketchId": "61649a3c1e0a596510ad8329",
      "value": 17,
      "extra": {
        "sketchName": "nearshore-span"
      }
    },
    {
      "reportId": "habitatProtection",
      "classId": "Bathypelagic",
      "metricId": "offshore",
      "sketchId": "61649a3c1e0a596510ad8329",
      "value": 11,
      "extra": {
        "sketchName": "nearshore-span"
      }
    },
    {
      "reportId": "habitatProtection",
      "classId": "Cold water coral",
      "metricId": "offshore",
      "sketchId": "61649a3c1e0a596510ad8329",
      "value": 0,
      "extra": {
        "sketchName": "nearshore-span"
      }
    },
    {
      "reportId": "habitatProtection",
      "classId": "Escarpments",
      "metricId": "offshore",
      "sketchId": "61649a3c1e0a596510ad8329",
      "value": 9,
      "extra": {
        "sketchName": "nearshore-span"
      }
    },
    {
      "reportId": "habitatProtection",
      "classId": "Knolls",
      "metricId": "offshore",
      "sketchId": "61649a3c1e0a596510ad8329",
      "value": 3,
      "extra": {
        "sketchName": "nearshore-span"
      }
    },
    {
      "reportId": "habitatProtection",
      "classId": "Pelagic zone 1",
      "metricId": "offshore",
      "sketchId": "61649a3c1e0a596510ad8329",
      "value": 30,
      "extra": {
        "sketchName": "nearshore-span"
      }
    },
    {
      "reportId": "habitatProtection",
      "classId": "Pelagic zone 2",
      "metricId": "offshore",
      "sketchId": "61649a3c1e0a596510ad8329",
      "value": 0,
      "extra": {
        "sketchName": "nearshore-span"
      }
    },
    {
      "reportId": "habitatProtection",
      "classId": "Pelagic zone 3",
      "metricId": "offshore",
      "sketchId": "61649a3c1e0a596510ad8329",
      "value": 0,
      "extra": {
        "sketchName": "nearshore-span"
      }
    },
    {
      "reportId": "habitatProtection",
      "classId": "Plains",
      "metricId": "offshore",
      "sketchId": "61649a3c1e0a596510ad8329",
      "value": 19,
      "extra": {
        "sketchName": "nearshore-span"
      }
    },
    {
      "reportId": "habitatProtection",
      "classId": "Seamounts",
      "metricId": "offshore",
      "sketchId": "61649a3c1e0a596510ad8329",
      "value": 0,
      "extra": {
        "sketchName": "nearshore-span"
      }
    }
  ],
  "sketch": {
    "type": "Feature",
    "properties": {
      "id": "61649a3c1e0a596510ad8329",
      "name": "nearshore-span",
      "updatedAt": "2021-10-11T20:10:36.004Z",
      "createdAt": "2021-10-11T20:10:36.004Z",
      "sketchClassId": "615b59e1aac8c8285d50d9b8",
      "isCollection": false,
      "userAttributes": [
        {
          "label": "Allowed Activities",
          "fieldType": "ChoiceField",
          "exportId": "ACTIVITIES",
          "value": "[\"RESEARCH\"]"
        }
      ]
    },
    "id": "1",
    "bbox": [
      -65.09902878851547,
      31.50541071353797,
      -64.79380174261453,
      32.28908133136779
    ],
    "geometry": null
  }
}